telnyx/__init__.py
telnyx/api_requestor.py
telnyx/error.py
telnyx/http_client.py
telnyx/multipart_data_generator.py
telnyx/request_metrics.py
telnyx/telnyx_object.py
telnyx/telnyx_response.py
telnyx/util.py
telnyx/webhook.py
telnyx/api_resources/__init__.py
telnyx/api_resources/access_control_ip.py
telnyx/api_resources/access_ip_address.py
telnyx/api_resources/access_token.py
telnyx/api_resources/address.py
telnyx/api_resources/advanced_optinoptout.py
telnyx/api_resources/ai.py
telnyx/api_resources/api_key.py
telnyx/api_resources/authentication_provider.py
telnyx/api_resources/autorechargepreference.py
telnyx/api_resources/available_phone_number.py
telnyx/api_resources/balance.py
telnyx/api_resources/billing.py
telnyx/api_resources/billing_group.py
telnyx/api_resources/brand.py
telnyx/api_resources/bucket.py
telnyx/api_resources/bucket_usage.py
telnyx/api_resources/bulk_creation.py
telnyx/api_resources/bulk_credential.py
telnyx/api_resources/bulk_phone_number_campaign.py
telnyx/api_resources/bulk_phone_number_operation.py
telnyx/api_resources/bulk_sole_proprietor_creation.py
telnyx/api_resources/business_identity.py
telnyx/api_resources/call.py
telnyx/api_resources/call_control_application.py
telnyx/api_resources/call_information.py
telnyx/api_resources/call_recording.py
telnyx/api_resources/campaign.py
telnyx/api_resources/cdr_usage_report.py
telnyx/api_resources/comment.py
telnyx/api_resources/conference.py
telnyx/api_resources/connection.py
telnyx/api_resources/credential_connection.py
telnyx/api_resources/csv_download.py
telnyx/api_resources/custom_storage_credential.py
telnyx/api_resources/customer_service_record.py
telnyx/api_resources/debugging.py
telnyx/api_resources/detail_record.py
telnyx/api_resources/detail_records_report.py
telnyx/api_resources/dialogflow_integration.py
telnyx/api_resources/document.py
telnyx/api_resources/dynamic_emergency_address.py
telnyx/api_resources/dynamic_emergency_endpoint.py
telnyx/api_resources/enum.py
telnyx-2.1.4.dist-info/LICENSE
telnyx-2.1.4.dist-info/METADATA
telnyx-2.1.4.dist-info/WHEEL
telnyx-2.1.4.dist-info/top_level.txt
telnyx-2.1.4.dist-info/RECORD
