Metadata-Version: 2.1
Name: telnyx
Version: 2.1.4
Summary: Python bindings for the Telnyx API
Home-page: https://github.com/team-telnyx/telnyx-python
Author: Telnyx
Author-email: support@telnyx.com
License: MIT
Project-URL: Documentation, https://developers.telnyx.com/docs/api/v2/overview
Project-URL: Source Code, https://github.com/team-telnyx/telnyx-python
Project-URL: Bug Tracker, https://github.com/team-telnyx/telnyx-python/issues
Keywords: telnyx telephony sip networking callcontrol messaging sms mms
Classifier: Development Status :: 5 - Production/Stable
Classifier: Intended Audience :: Developers
Classifier: License :: OSI Approved :: MIT License
Classifier: Operating System :: OS Independent
Classifier: Programming Language :: Python
Classifier: Programming Language :: Python :: 3
Classifier: Programming Language :: Python :: 3.8
Classifier: Programming Language :: Python :: 3.9
Classifier: Programming Language :: Python :: 3.10
Classifier: Programming Language :: Python :: 3.11
Classifier: Programming Language :: Python :: 3.12
Classifier: Programming Language :: Python :: Implementation :: PyPy
Classifier: Topic :: Communications :: Telephony
Classifier: Topic :: Software Development :: Libraries :: Python Modules
Requires-Python: >=3.8
License-File: LICENSE
Requires-Dist: requests>=2.20
Requires-Dist: six>=1.16.0
Requires-Dist: PyNaCl
